{
  "navLabel": "DÍA 1 · SAB 15 AGO",
  "navName": "Mérida",
  "ready": true,
  "title": "Redován → Mérida",
  "date": "Sábado, 15 de agosto de 2026",
  "subtitle": "La antigua Augusta Emerita, capital de la Lusitania romana y Patrimonio de la Humanidad. Una de las ciudades con más densidad de restos romanos del mundo.",
  "alerts": [],
  "sections": [
    {
      "name": "Ruta completa del día",
      "content": "\n        <div class=\"stop\">\n          <div class=\"stop-body\" style=\"display: block; padding: 1rem;\">\n            <div class=\"stop-desc\" style=\"margin: 0;\">Ruta de Google Maps con todas las paradas del día 1 en orden: desde Redován hasta Mérida, pasando por todos los monumentos visitados.</div>\n            <a class=\"maps-btn\" href=\"https://www.google.com/maps/dir/Redován,+España/Mérida,+España/Termas+de+San+Lázaro,+Mérida/Cripta+Arqueológica+de+Santa+Eulalia,+Mérida/Teatro+Romano+Mérida/Pórtico+del+Foro+Municipal,+Mérida/Templo+de+Diana,+Mérida/Arco+de+Trajano,+Mérida/Plaza+de+España,+Mérida/Puente+Romano+Mérida\" target=\"_blank\" style=\"margin-top: 1rem;\">📍 Ver ruta completa en Google Maps</a>\n          </div>\n        </div>\n      "
    },
    {
      "name": "El viaje",
      "distance": "≈ 620 km · 6h 45min",
      "stops": [
        {
          "icon": "🚗",
          "iconClass": "icon-walk",
          "name": "Redován → Mérida",
          "pills": [
            {"type": "blue", "text": "6h 45min aprox."}
          ],
          "meta": [
            "📍 A-7 / A-30 / A-4 / A-5",
            "~620 km"
          ],
          "description": "Ruta más habitual: salir por la A-7 dirección Murcia → tomar la A-30 hacia Albacete → conectar con la A-4 hacia Madrid → desviarse por la A-43 hacia Mérida via Badajoz. Es un trayecto largo, recomendable hacer paradas para descansar.",
          "items": [
            "Salida recomendada: 7h00–7h30 para llegar a Mérida a eso de las 14h",
            "Peajes: la ruta no tiene peajes significativos en España",
            "Aparcamiento en Mérida: hay parking gratuito cerca del Teatro Romano (Av. Margarita Xirgu) y aparcamiento en el Paseo de Roma"
          ],
          "mapsLink": "https://maps.google.com/?saddr=Redován,+España&daddr=Mérida,+España",
          "mapsText": "Ruta en Google Maps"
        }
      ],
      "driveTime": "🚶 ~13 min a pie"
    },
    {
      "name": "1ª parada — Termas de San Lázaro",
      "distance": "Al llegar a Mérida · Norte de la ciudad",
      "stops": [
        {
          "icon": "♨️",
          "iconClass": "icon-free",
          "name": "Termas de San Lázaro",
          "pills": [
            {"type": "free", "text": "Entrada gratuita"}
          ],
          "meta": [
            "⏱ 10–15 min",
            "🕐 Abierto 24h"
          ],
          "description": "Restos de un complejo termal público construido a principios del siglo II d.C. sobre unas instalaciones industriales anteriores. Se abastecía del agua que transportaba el cercano Acueducto de San Lázaro. Las termas estuvieron en funcionamiento hasta el siglo III. Aunque los restos son modestos comparados con otros monumentos de la ciudad, merece la pena la parada rápida ya que están de camino y son gratuitas.",
          "items": [
            "Podían apreciarse distintas estancias: vestuario, sala de vapor, dos piscinas de agua caliente y una de agua fría",
            "A pocos metros se encuentran las columnas originales del Acueducto de San Lázaro — también gratuito y muy fotogénico",
            "Están junto al Circo Romano, también visitable",
            "Honestamente: los restos son escasos. Es parada de 10 minutos, no más"
          ],
          "ticketBox": "<strong>Precio:</strong> Gratuito · Visita libre · Abierto 24h<br><strong>Dirección:</strong> Av. Juan Carlos I, Mérida (junto al Acueducto de San Lázaro)",
          "mapsLink": "https://maps.google.com/?q=Termas+de+San+Lázaro+Mérida",
          "mapsText": "Ver en Google Maps"
        }
      ],
      "driveTime": "🚶 10 min a pie"
    },
    {
      "name": "2ª parada — Cripta de Santa Eulalia",
      "distance": "Av. de Extremadura · ~10 min de las Termas",
      "stops": [
        {
          "icon": "⛪",
          "iconClass": "icon-pay",
          "name": "Cripta Arqueológica de Santa Eulalia",
          "pills": [
            {"type": "price", "text": "Incluido en combo 17,50 €"}
          ],
          "meta": [
            "⏱ 25–35 min",
            "🕐 9h–21h"
          ],
          "description": "Bajo la actual basílica dedicada a la patrona de Mérida se esconden más de 2.000 años de historia apilados en capas. Es uno de los yacimientos arqueológicos más fascinantes de España: puedes ver, literalmente, una casa romana del siglo I, encima un martyrium paleocristiano del siglo IV, encima una iglesia visigoda del siglo V, y encima la basílica actual.",
          "items": [
            "<strong>Eulalia</strong> fue una joven de 12 años martirizada bajo el emperador Diocleciano en el 304 d.C. por negarse a rendir culto a los dioses romanos. Desde entonces es una de las santas más veneradas de Hispania",
            "El recorrido subterráneo muestra la superposición de las distintas épocas históricas",
            "Hay piezas de gran valor: capiteles, sepulturas, mosaicos y cerámica romana"
          ],
          "ticketBox": "<strong>Horario:</strong> 9h–21h (verano) · <strong>Incluido</strong> en el ticket combinado del Consorcio (15 €)",
          "mapsLink": "https://maps.google.com/?q=Cripta+Basílica+Santa+Eulalia+Mérida",
          "mapsText": "Ver en Google Maps"
        }
      ],
      "driveTime": "🚶 ~5 min a pie"
    },
    {
      "name": "3ª parada — Teatro y Anfiteatro Romano",
      "distance": "C/ José Ramón Mélida · ~8 min de la Cripta",
      "stops": [
        {
          "icon": "🎭",
          "iconClass": "icon-pay",
          "name": "Teatro Romano de Mérida",
          "pills": [
            {"type": "price", "text": "Incluido en combo 17,50 €"}
          ],
          "meta": [
            "⏱ 1h–1h 30min (ambos)",
            "🕐 9h–21h · Última entrada 20h30",
            "🏛 UNESCO"
          ],
          "description": "Construido entre los años 16 y 15 a.C. bajo el patrocinio de Marco Agripa, yerno del emperador Augusto. Es uno de los teatros romanos mejor conservados del mundo. La scaenae frons — el fondo escénico con dos pisos de columnas corintias y estatuas originales — es literalmente deslumbrante. Tenía capacidad para 6.000 espectadores distribuidos en tres sectores de gradas según el rango social.",
          "items": [
            "La mayoría de las columnas del frente escénico son originales romanas, no reconstrucciones",
            "Sigue en uso: cada verano el Festival de Teatro Clásico llena sus gradas con obras de Sófocles, Eurípides o Aristófanes",
            "Bajo la orchestra quedan restos de mosaicos de mármol originales",
            "El acceso a los restos de la Casa del Anfiteatro (con mosaicos) también está incluido en el combo"
          ],
          "ticketBox": "<strong>💡 Compra el ticket combinado (17,50 €):</strong> cubre Teatro, Anfiteatro, Cripta de Santa Eulalia y Templo de Diana (todos los que visitáis hoy). <br><strong>Horario:</strong> 9h–21h (abr–sep) · Última entrada 20h30<br><strong>Reducida:</strong> 8 € (jóvenes 13–17 años, estudiantes hasta 25, mayores de 65, discapacidad)<br><strong>Gratis:</strong> menores de 13 años acompañados<br><a href=\"https://consorciomerida.sacatuentrada.es/es/lotes/circuito-sin-guia-teatro-anfiteatro-2020\" target=\"_blank\">→ Comprar online en consorciomerida.org</a>",
          "mapsLink": "https://maps.google.com/?q=Teatro+Romano+Mérida",
          "mapsText": "Ver en Google Maps"
        },
        {
          "icon": "⚔️",
          "iconClass": "icon-pay",
          "name": "Anfiteatro Romano",
          "pills": [
            {"type": "price", "text": "Incluido en combo 17,50 €"}
          ],
          "meta": [
            "⏱ 20–30 min",
            "🕐 9h–21h",
            "🏛 UNESCO"
          ],
          "description": "Construido en el año 8 a.C., era el lugar donde se celebraban los espectáculos más brutales del mundo romano: luchas de gladiadores, caza de animales salvajes y ejecuciones públicas. Tenía capacidad para 15.000 espectadores. Los restos son menos espectaculares que los del teatro, pero la visita merece la pena por la atmósfera y por ver la Casa del Anfiteatro.",
          "items": [
            "El anfiteatro tenía forma elíptica y estaba rodeado por un muro de 3 metros de altura",
            "En el centro se encontraba la arena, donde se desarrollaban los espectáculos",
            "Bajo la arena había pasillos y cámaras donde se guardaban los gladiadores y los animales",
            "La Casa del Anfiteatro, adyacente, tiene mosaicos bien conservados"
          ],
          "mapsLink": "https://maps.google.com/?q=Anfiteatro+Romano+Mérida",
          "mapsText": "Ver en Google Maps"
        }
      ],
      "driveTime": "🚶 ~2 min a pie"
    },
    {
      "name": "4ª parada — Pórtico del Foro Municipal",
      "distance": "Calle Sagasta · ~5 min del Teatro",
      "stops": [
        {
          "icon": "🏺",
          "iconClass": "icon-free",
          "name": "Pórtico del Foro Municipal",
          "pills": [
            {"type": "free", "text": "Entrada gratuita"}
          ],
          "meta": [
            "⏱ 10 min",
            "🕐 9h–21h"
          ],
          "description": "Restos del pórtico que rodeaba el Foro Municipal de Augusta Emerita, el centro administrativo y judicial de la ciudad romana. Se pueden ver columnas y fragmentos arquitectónicos del siglo I d.C. asomando entre los edificios actuales de la Calle Sagasta — uno de esos momentos en que la historia literalmente emerge del asfalto.",
          "items": [
            "El Foro Municipal era el equivalente al ayuntamiento romano: aquí se impartía justicia y se tomaban decisiones políticas",
            "Los restos son accesibles y visibles desde la calle, perfectamente señalizados",
            "Merece la pena pararse a leer los paneles explicativos para entender la magnitud de lo que hubo aquí"
          ],
          "mapsLink": "https://maps.google.com/?q=Pórtico+del+Foro+Municipal+Mérida+Calle+Sagasta",
          "mapsText": "Ver en Google Maps"
        }
      ],
      "driveTime": "🚶 5 min a pie"
    },
    {
      "name": "5ª parada — Templo de Diana",
      "distance": "2 min del Pórtico",
      "stops": [
        {
          "icon": "🏛️",
          "iconClass": "icon-pay",
          "name": "Templo de Diana",
          "pills": [
            {"type": "price", "text": "Incluido en combo 17,50 €"}
          ],
          "meta": [
            "⏱ 20 min",
            "🕐 9h–21h · Última entrada 20h30"
          ],
          "description": "Uno de los templos romanos mejor conservados de España, del siglo I a.C. La razón de su supervivencia es curiosa y fascinante: en el siglo XVI un noble renacentista, el Conde de los Corbos, construyó su palacio directamente dentro del templo, incorporando las columnas romanas como parte de su estructura. Eso lo protegió de ser desmontado para usar sus piedras en otras construcciones.",
          "items": [
            "El nombre 'Templo de Diana' es un error del Renacimiento — en realidad estaba dedicado al culto imperial, no a la diosa Diana",
            "Quedan en pie 11 columnas corintias con arquitrabas y parte del pódium original",
            "Dentro del recinto se puede ver perfectamente la superposición del palacio renacentista sobre la estructura romana",
            "El interior alberga hoy el Centro de Interpretación, incluido en el combo"
          ],
          "ticketBox": "<strong>Nota:</strong> La taquilla del Templo de Diana solo vende la entrada individual de este monumento. Para el combo de 15 € hay que comprarlo en la taquilla del Teatro Romano o en la web.",
          "mapsLink": "https://maps.google.com/?q=Templo+de+Diana+Mérida",
          "mapsText": "Ver en Google Maps"
        }
      ],
      "driveTime": "🚶 ~3 min a pie"
    },
    {
      "name": "6ª parada — Arco de Trajano",
      "distance": "2 min del Templo de Diana",
      "stops": [
        {
          "icon": "🏟️",
          "iconClass": "icon-free",
          "name": "Arco de Trajano",
          "pills": [
            {"type": "free", "text": "Entrada gratuita"}
          ],
          "meta": [
            "⏱ 10 min",
            "🕐 Acceso libre"
          ],
          "description": "Un arco monumental de más de 15 metros de altura, construido en el siglo I d.C. A pesar de su nombre popular, probablemente no tiene relación directa con el emperador Trajano. Era la puerta de acceso al témenos, el recinto sagrado que rodeaba el gran templo del foro de Mérida. Impresiona ver cómo el arco se integra en la trama urbana actual, con casas literalmente apoyadas en él durante siglos.",
          "items": [
            "Construido en granito local con sillares perfectamente encajados, sin argamasa",
            "Es un arco de un solo vano, de estilo austero y muy diferente a los arcos triunfales ornamentados típicos de Roma",
            "Durante siglos sirvió como puerta de entrada a la ciudad medieval"
          ],
          "mapsLink": "https://maps.google.com/?q=Arco+de+Trajano+Mérida",
          "mapsText": "Ver en Google Maps"
        }
      ],
      "driveTime": "🚶 5 min a pie"
    },
    {
      "name": "7ª parada — Plaza de España",
      "distance": "3 min del Arco",
      "stops": [
        {
          "icon": "🏛️",
          "iconClass": "icon-free",
          "name": "Plaza de España y sus monumentos",
          "pills": [
            {"type": "free", "text": "Entrada gratuita"}
          ],
          "meta": [
            "⏱ 20–30 min"
          ],
          "description": "La plaza mayor de Mérida, rodeada de edificios históricos de distintas épocas. Es el corazón social y político de la ciudad, con terrazas y ambiente especialmente animado en verano. Todos los edificios son para ver desde el exterior.",
          "items": [
            "<strong>Palacio de los Mendoza</strong> — Edificio renacentista del siglo XVI, hoy sede del Ayuntamiento. Fachada con escudo heráldico monumental",
            "<strong>Casa de los Pacheco</strong> — Palacio nobiliario del siglo XVI con hermosa portada",
            "<strong>Círculo Emeritense</strong> — Casino y club social del siglo XIX, con fachada modernista muy decorada",
            "<strong>Concatedral de Santa María la Mayor</strong> — Heredera de la antigua catedral visigoda. Interior renacentista con elementos medievales. Vale la pena entrar si está abierta"
          ],
          "mapsLink": "https://maps.google.com/?q=Plaza+de+España+Mérida+España",
          "mapsText": "Ver en Google Maps"
        }
      ],
      "driveTime": "🚶 5 min a pie"
    },
    {
      "name": "8ª parada — Puente Romano",
      "distance": "Río Guadiana · 8 min de Plaza de España",
      "stops": [
        {
          "icon": "🌉",
          "iconClass": "icon-free",
          "name": "Puente Romano sobre el Guadiana",
          "pills": [
            {"type": "free", "text": "Entrada gratuita"}
          ],
          "meta": [
            "⏱ 20–30 min",
            "🕐 Peatonal, acceso libre"
          ],
          "description": "El puente más largo de todos los que se conservan de la antigua Roma: 792 metros de longitud y 60 arcos. Construido en el siglo I d.C., sigue en uso hoy en día — eso sí, solo para peatones. Es una de las imágenes más icónicas de Mérida, especialmente al atardecer cuando el sol se pone tras el puente.",
          "items": [
            "El puente formaba parte de la Vía de la Plata, la calzada romana que unía Mérida con Astorga",
            "En el centro del puente hay una torre fortificada medieval añadida posteriormente",
            "Desde el puente se tienen las mejores vistas de la ciudad y del río Guadiana",
            "Es el lugar perfecto para terminar el día con un paseo y fotos al atardecer"
          ],
          "mapsLink": "https://maps.google.com/?q=Puente+Romano+Mérida",
          "mapsText": "Ver en Google Maps"
        }
      ]
    }
  ],
  "timeline": [
    "Llegada a Mérida · Aparcamiento y Termas de San Lázaro (15 min)",
    "Cripta de Santa Eulalia — 30 min",
    "Teatro Romano + Anfiteatro — 1h 30min · Comprar combo aquí",
    "Pórtico del Foro Municipal — 10 min",
    "Templo de Diana — 20 min",
    "Arco de Trajano — 10 min",
    "Plaza de España + monumentos alrededor — 25 min",
    "Puente Romano sobre el Guadiana — 25 min",
    "✅ Fin del recorrido · Descanso / Cena / Noche en Mérida"
  ],
  "summary": {
    "title": "Entradas · Día 1 · por persona",
    "rows": [
      {"label": "Termas de San Lázaro", "value": "Gratis"},
      {"label": "Teatro Romano + Anfiteatro + Cripta + Templo Diana", "value": "15 € (combo)"},
      {"label": "Plaza de España, Arco de Trajano, Foro Municipal, Puente Romano", "value": "Gratis"}
    ],
    "total": {
      "label": "Total entradas por persona",
      "value": "15 €"
    }
  }
}